chronolap/__init__.py
chronolap/chronolap.py
chronolap-1.0.1.dist-info/licenses/LICENSE
chronolap-1.0.1.dist-info/METADATA
chronolap-1.0.1.dist-info/WHEEL
chronolap-1.0.1.dist-info/top_level.txt
chronolap-1.0.1.dist-info/RECORD
