Metadata-Version: 2.4
Name: chronolap
Version: 1.0.1
Summary: Advanced stopwatch with lap tracking for Python developers
Home-page: https://github.com/ertugrulkara/ChronolapPy
Author: Ertugrul Kara
Author-email: Ertugrul Kara <your-email@example.com>
License: MIT
Classifier: Programming Language :: Python :: 3
Classifier: License :: OSI Approved :: MIT License
Classifier: Operating System :: OS Independent
Requires-Python: >=3.7
License-File: LICENSE
Dynamic: author
Dynamic: home-page
Dynamic: license-file
Dynamic: requires-python
